{
  "version": "1.0.0",
  "releaseDate": "2026-05-07",
  "compatibleWith": ">=1.0.0",
  "changelog": {
    "1.0.0": [
      "Phase 1.1: 基础设施 (认证/数据库/组织架构/UI布局/权限)",
      "Phase 1.2: 资产管理中心 (8大品类CRUD/筛选/文档上传/仪表板)",
      "Phase 1.3: 审批工作流 (领用/归还/调拨/报废 完整闭环)",
      "Phase 2.1: 到期提醒 (维保/证书到期扫描+定时任务)",
      "Phase 2.2: 批量导入导出 (CSV导入/导出/模板下载/错误报告)",
      "Phase 2.3: 版本升级方案 (Docker+一键升级脚本)",
      "Phase 3.1: 审计日志 + H5移动端适配 (底部导航/汉堡菜单/响应式)",
      "Phase 3.2: Docker多架构构建 + 完整部署文档 (麒麟/欧拉/Ubuntu)"
    ]
  },
  "upgrade": {
    "method": "docker",
    "commands": [
      "docker pull haooy1/asset-manager:latest",
      "docker-compose down",
      "docker-compose up -d",
      "docker exec -it asset-manager npx prisma db push"
    ]
  }
}
